cybershuttle_tune/__init__.py
cybershuttle_tune/airavata_operator.py
cybershuttle_tune/cli/__init__.py
cybershuttle_tune/cli/auth.py
cybershuttle_tune/cli/main.py
cybershuttle_tune/param_types.py
cybershuttle_tune/parser.py
cybershuttle_tune/sdk.py
cybershuttle_tune/sweeper.py
cybershuttle_tune-0.1.19.dist-info/LICENSE
cybershuttle_tune-0.1.19.dist-info/METADATA
cybershuttle_tune-0.1.19.dist-info/WHEEL
cybershuttle_tune-0.1.19.dist-info/entry_points.txt
cybershuttle_tune-0.1.19.dist-info/RECORD
